refractiveindexlibrary/__init__.py
refractiveindexlibrary/refractiveindexlibrary.py
refractiveindexlibrary-0.0.5.dist-info/LICENSE
refractiveindexlibrary-0.0.5.dist-info/METADATA
refractiveindexlibrary-0.0.5.dist-info/WHEEL
refractiveindexlibrary-0.0.5.dist-info/RECORD
