Metadata-Version: 2.3
Name: refractiveindexlibrary
Version: 0.0.5
Summary: 
Author: Victor Liu
Author-email: victor.liu@gmail.com
Requires-Python: >=3.9,<4.0
Classifier: Programming Language :: Python :: 3
Classifier: Programming Language :: Python :: 3.9
Classifier: Programming Language :: Python :: 3.10
Classifier: Programming Language :: Python :: 3.11
Classifier: Programming Language :: Python :: 3.12
Classifier: Programming Language :: Python :: 3.13
Requires-Dist: pyyaml (>=6.0,<7.0)
Requires-Dist: scipy (>=1.9.3,<2.0.0)
